<?xml version="1.0" encoding="UTF-8"?>
<record_update sys_domain="5f33c0b1dbb8df401bfdef92ca9619fd" table="pa_dashboards">
    <pa_dashboards action="INSERT_OR_UPDATE">
        <active>false</active>
        <breakdown_source/>
        <group display_value="CMDB Dashboard">1d76d453eb1122007c074d3df106fe50</group>
        <groups/>
        <is_breakdown>false</is_breakdown>
        <managed_breakdown/>
        <managed_publisher/>
        <name>CMDB Service Completeness Dashboard</name>
        <no_tabs>false</no_tabs>
        <order>560</order>
        <owner display_value="Robert Thomas">76bb962adb5b1b001bfdef92ca961969</owner>
        <restrict_to_roles>pa_viewer,pa_contributor</restrict_to_roles>
        <role_override>true</role_override>
        <roles>asset,itil</roles>
        <should_migrate_permissions>false</should_migrate_permissions>
        <sys_class_name>pa_dashboards</sys_class_name>
        <sys_created_by>rthomas@tricorp-itsolutions.com</sys_created_by>
        <sys_created_on>2018-04-06 13:16:31</sys_created_on>
        <sys_customer_update>false</sys_customer_update>
        <sys_domain>5f33c0b1dbb8df401bfdef92ca9619fd</sys_domain>
        <sys_domain_path/>
        <sys_id>f89e8079dbd113c0e3a506e2ca9619e8</sys_id>
        <sys_mod_count>3</sys_mod_count>
        <sys_name>CMDB Service Completeness Dashboard</sys_name>
        <sys_overrides display_value="CMDB Service Completeness Dashboard">dfa98af6ebf3120078e44d3df106feb8</sys_overrides>
        <sys_package display_value="TRICODE" source="x_4s_tricode">8912fb2adb789380e3a506e2ca961972</sys_package>
        <sys_policy/>
        <sys_replace_on_upgrade>false</sys_replace_on_upgrade>
        <sys_scope display_value="TRICODE">8912fb2adb789380e3a506e2ca961972</sys_scope>
        <sys_update_name>pa_dashboards_f89e8079dbd113c0e3a506e2ca9619e8</sys_update_name>
        <sys_updated_by>rthomas@tricorp-itsolutions.com</sys_updated_by>
        <sys_updated_on>2018-04-06 16:13:39</sys_updated_on>
        <users/>
        <visible_to>2</visible_to>
    </pa_dashboards>
</record_update>
